ansys/dpf/core/__init__.py
ansys/dpf/core/_custom_operators_helpers.py
ansys/dpf/core/_model_helpers.py
ansys/dpf/core/_version.py
ansys/dpf/core/animation.py
ansys/dpf/core/animator.py
ansys/dpf/core/any.py
ansys/dpf/core/available_result.py
ansys/dpf/core/cache.py
ansys/dpf/core/changelog.py
ansys/dpf/core/check_version.py
ansys/dpf/core/collection.py
ansys/dpf/core/collection_base.py
ansys/dpf/core/common.py
ansys/dpf/core/config.py
ansys/dpf/core/core.py
ansys/dpf/core/custom_container_base.py
ansys/dpf/core/custom_fields_container.py
ansys/dpf/core/custom_operator.py
ansys/dpf/core/custom_type_field.py
ansys/dpf/core/cyberchannel.py
ansys/dpf/core/cyclic_support.py
ansys/dpf/core/data_sources.py
ansys/dpf/core/data_tree.py
ansys/dpf/core/dimensionality.py
ansys/dpf/core/dpf_array.py
ansys/dpf/core/dpf_operator.py
ansys/dpf/core/element_descriptor.py
ansys/dpf/core/elements.py
ansys/dpf/core/errors.py
ansys/dpf/core/faces.py
ansys/dpf/core/field.py
ansys/dpf/core/field_base.py
ansys/dpf/core/field_definition.py
ansys/dpf/core/fields_container.py
ansys/dpf/core/fields_container_factory.py
ansys/dpf/core/fields_factory.py
ansys/dpf/core/generic_data_container.py
ansys/dpf/core/generic_support.py
ansys/dpf/core/geometry.py
ansys/dpf/core/geometry_factory.py
ansys/dpf/core/help.py
ansys/dpf/core/incremental.py
ansys/dpf/core/inputs.py
ansys/dpf/core/ipconfig.py
ansys/dpf/core/label_space.py
ansys/dpf/core/log.py
ansys/dpf/core/mapping_types.py
ansys/dpf/core/mesh_info.py
ansys/dpf/core/mesh_scoping_factory.py
ansys/dpf/core/meshed_region.py
ansys/dpf/core/meshes_container.py
ansys/dpf/core/misc.py
ansys/dpf/core/model.py
ansys/dpf/core/nodes.py
ansys/dpf/core/operator_specification.py
ansys/dpf/core/outputs.py
ansys/dpf/core/path_utilities.py
ansys/dpf/core/plotter.py
ansys/dpf/core/plugins.py
ansys/dpf/core/property_field.py
ansys/dpf/core/property_fields_container.py
ansys/dpf/core/result_info.py
ansys/dpf/core/results.py
ansys/dpf/core/runtime_config.py
ansys_dpf_core-0.15.0.dist-info/licenses/AUTHORS
ansys_dpf_core-0.15.0.dist-info/licenses/LICENSE
ansys_dpf_core-0.15.0.dist-info/METADATA
ansys_dpf_core-0.15.0.dist-info/WHEEL
ansys_dpf_core-0.15.0.dist-info/entry_points.txt
ansys_dpf_core-0.15.0.dist-info/top_level.txt
ansys_dpf_core-0.15.0.dist-info/RECORD
