Metadata-Version: 2.4
Name: ansys-dpf-core
Version: 0.15.0
Summary: Data Processing Framework - Python Core 
Author-email: "ANSYS, Inc." <pyansys.core@ansys.com>
Maintainer-email: "ANSYS, Inc." <pyansys.core@ansys.com>
License: MIT License
Project-URL: Homepage, https://dpf.docs.pyansys.com/
Project-URL: Documentation, https://dpf.docs.pyansys.com/
Project-URL: Source, https://github.com/ansys/pydpf-core
Project-URL: Tracker, https://github.com/ansys/pydpf-core/issues
Classifier: Development Status :: 4 - Beta
Classifier: Intended Audience :: Science/Research
Classifier: Topic :: Scientific/Engineering :: Information Analysis
Classifier: License :: OSI Approved :: MIT License
Classifier: Operating System :: Microsoft :: Windows
Classifier: Operating System :: POSIX
Classifier: Programming Language :: Python :: 3
Requires-Python: <4,>=3.9
License-File: LICENSE
License-File: AUTHORS
Requires-Dist: grpcio>=1.63.0
Requires-Dist: importlib-metadata>=4.0
Requires-Dist: numpy
Requires-Dist: packaging
Requires-Dist: protobuf
Requires-Dist: psutil
Requires-Dist: setuptools
Requires-Dist: tqdm
Provides-Extra: graphics
Requires-Dist: matplotlib>=3.2; extra == "graphics"
Requires-Dist: pyvista>=0.32.0; extra == "graphics"
Requires-Dist: vtk!=9.4.0; extra == "graphics"
Requires-Dist: imageio; extra == "graphics"
Requires-Dist: imageio-ffmpeg; extra == "graphics"
Provides-Extra: plotting
Requires-Dist: matplotlib>=3.2; extra == "plotting"
Requires-Dist: pyvista>=0.32.0; extra == "plotting"
Requires-Dist: vtk; extra == "plotting"
Requires-Dist: imageio; extra == "plotting"
Requires-Dist: imageio-ffmpeg; extra == "plotting"
Provides-Extra: operator-doc
Requires-Dist: jinja2; extra == "operator-doc"
Dynamic: license-file
